kkloader/AicomiCharaData.py
kkloader/EmocreCharaData.py
kkloader/EmocreMapData.py
kkloader/EmocreSceneData.py
kkloader/HoneycomeCharaData.py
kkloader/KoikatuCharaData.py
kkloader/KoikatuSaveData.py
kkloader/SummerVacationCharaData.py
kkloader/SummerVacationSaveData.py
kkloader/__init__.py
kkloader/funcs.py
kkloader-0.1.12.dist-info/METADATA
kkloader-0.1.12.dist-info/WHEEL
kkloader-0.1.12.dist-info/RECORD
