Metadata-Version: 2.4
Name: kkloader
Version: 0.1.12
Summary: a simple deserializer / serializer for Koikatu / EmotionCreators / Honeycome / SummerVacationScramble data.
Author: great-majority
Author-email: wired.wireless0@gmail.com
Requires-Python: >=3.11,<4.0
Classifier: Programming Language :: Python :: 3
Classifier: Programming Language :: Python :: 3.11
Classifier: Programming Language :: Python :: 3.12
Classifier: Programming Language :: Python :: 3.13
Classifier: Programming Language :: Python :: 3.14
Requires-Dist: lz4 (>=4.4.4,<5.0.0)
Requires-Dist: msgpack (>=1.0.3,<2.0.0)
Requires-Dist: pandas (>=2.2.2,<3.0.0)
Project-URL: Homepage, https://github.com/great-majority/KoikatuCharaLoader
